setup.py
hey_distributions/Binomialdistribution.py
hey_distributions/Gaussiandistribution.py
hey_distributions/Generaldistribution.py
hey_distributions/__init__.py
hey_distributions.egg-info/PKG-INFO
hey_distributions.egg-info/SOURCES.txt
hey_distributions.egg-info/dependency_links.txt
hey_distributions.egg-info/not-zip-safe
hey_distributions.egg-info/top_level.txt